fileStorage3/__init__.py
fileStorage3/disk.py
fileStorage3/fileStorage3.py
fileStorage3/fileSystem.py
fileStorage3/s3.py
fileStorage3-0.0.3.dist-info/LICENSE
fileStorage3-0.0.3.dist-info/METADATA
fileStorage3-0.0.3.dist-info/WHEEL
fileStorage3-0.0.3.dist-info/top_level.txt
fileStorage3-0.0.3.dist-info/RECORD
